MANIFEST.in
README.txt
bootstrap.py
buildout.cfg
setup.py
blockdiagcontrib/__init__.py
blockdiagcontrib/labeled_box.py
blockdiagcontrib_labeledbox.egg-info/PKG-INFO
blockdiagcontrib_labeledbox.egg-info/SOURCES.txt
blockdiagcontrib_labeledbox.egg-info/dependency_links.txt
blockdiagcontrib_labeledbox.egg-info/entry_points.txt
blockdiagcontrib_labeledbox.egg-info/namespace_packages.txt
blockdiagcontrib_labeledbox.egg-info/requires.txt
blockdiagcontrib_labeledbox.egg-info/top_level.txt